l5kit/__init__.py
l5kit/cle/__init__.py
l5kit/cle/closed_loop_evaluator.py
l5kit/cle/composite_metrics.py
l5kit/cle/metric_set.py
l5kit/cle/metrics.py
l5kit/cle/scene_type_agg.py
l5kit/cle/validators.py
l5kit/configs/__init__.py
l5kit/configs/config.py
l5kit/data/__init__.py
l5kit/data/combine.py
l5kit/data/filter.py
l5kit/data/labels.py
l5kit/data/local_data_manager.py
l5kit/data/map_api.py
l5kit/data/zarr_dataset.py
l5kit/data/zarr_utils.py
l5kit/data/proto/__init__.py
l5kit/data/proto/road_network_pb2.py
l5kit/dataset/__init__.py
l5kit/dataset/agent.py
l5kit/dataset/ego.py
l5kit/dataset/select_agents.py
l5kit/dataset/utils.py
l5kit/environment/__init__.py
l5kit/environment/callbacks.py
l5kit/environment/feature_extractor.py
l5kit/environment/gym_metric_set.py
l5kit/environment/kinematic_model.py
l5kit/environment/models.py
l5kit/environment/reward.py
l5kit/environment/utils.py
l5kit/environment/envs/__init__.py
l5kit/environment/envs/l5_env.py
l5kit/evaluation/__init__.py
l5kit/evaluation/chop_dataset.py
l5kit/evaluation/csv_utils.py
l5kit/evaluation/error_functions.py
l5kit/evaluation/extract_ground_truth.py
l5kit/evaluation/extract_metrics.py
l5kit/evaluation/metrics.py
l5kit/geometry/__init__.py
l5kit/geometry/angle.py
l5kit/geometry/image.py
l5kit/geometry/transform.py
l5kit/geometry/voxel.py
l5kit/kinematic/__init__.py
l5kit/kinematic/ackerman_perturbation.py
l5kit/kinematic/ackerman_steering_model.py
l5kit/kinematic/perturbation.py
l5kit/planning/__init__.py
l5kit/planning/utils.py
l5kit/planning/rasterized/__init__.py
l5kit/planning/rasterized/model.py
l5kit/planning/vectorized/__init__.py
l5kit/planning/vectorized/closed_loop_model.py
l5kit/planning/vectorized/common.py
l5kit/planning/vectorized/global_graph.py
l5kit/planning/vectorized/local_graph.py
l5kit/planning/vectorized/open_loop_model.py
l5kit/random/__init__.py
l5kit/random/random_generator.py
l5kit/rasterization/__init__.py
l5kit/rasterization/box_rasterizer.py
l5kit/rasterization/rasterizer.py
l5kit-1.5.0.dist-info/METADATA
l5kit-1.5.0.dist-info/WHEEL
l5kit-1.5.0.dist-info/top_level.txt
l5kit-1.5.0.dist-info/RECORD
